{"lastDay":{"type":"BigNumber","hex":"0x4d52"},"rewards":[{"type":"interest","period":"long","time":{"type":"BigNumber","hex":"0x65e7b200"},"amount":{"type":"BigNumber","hex":"0xaf7687d5"}},{"type":"interest","period":"long","time":{"type":"BigNumber","hex":"0x65e90380"},"amount":{"type":"BigNumber","hex":"0xb0813ef1"}},{"type":"interest","period":"long","time":{"type":"BigNumber","hex":"0x65ea5500"},"amount":{"type":"BigNumber","hex":"0xb1952880"}},{"type":"interest","period":"long","time":{"type":"BigNumber","hex":"0x65eba680"},"amount":{"type":"BigNumber","hex":"0xb9cf4a05"}},{"type":"interest","period":"long","time":{"type":"BigNumber","hex":"0x65ecf800"},"amount":{"type":"BigNumber","hex":"0xbaf5987c"}},{"type":"interest","period":"long","time":{"type":"BigNumber","hex":"0x65ee4980"},"amount":{"type":"BigNumber","hex":"0xbc12b47f"}},{"type":"interest","period":"long","time":{"type":"BigNumber","hex":"0x65ef9b00"},"amount":{"type":"BigNumber","hex":"0xbd2fd082"}}]}