{"lastDay":{"type":"BigNumber","hex":"0x4c4f"},"rewards":[{"type":"interest","period":"long","time":{"type":"BigNumber","hex":"0x6490ec00"},"amount":{"type":"BigNumber","hex":"0x0169f49073"}},{"type":"interest","period":"long","time":{"type":"BigNumber","hex":"0x64923d80"},"amount":{"type":"BigNumber","hex":"0x0169f49073"}},{"type":"interest","period":"long","time":{"type":"BigNumber","hex":"0x64938f00"},"amount":{"type":"BigNumber","hex":"0x0169f49073"}},{"type":"interest","period":"long","time":{"type":"BigNumber","hex":"0x6494e080"},"amount":{"type":"BigNumber","hex":"0x016a9bf37a"}},{"type":"interest","period":"long","time":{"type":"BigNumber","hex":"0x64963200"},"amount":{"type":"BigNumber","hex":"0x016a9bf37a"}},{"type":"interest","period":"long","time":{"type":"BigNumber","hex":"0x64978380"},"amount":{"type":"BigNumber","hex":"0x016a9bf37a"}},{"type":"interest","period":"long","time":{"type":"BigNumber","hex":"0x6498d500"},"amount":{"type":"BigNumber","hex":"0x016a9bf37a"}},{"type":"interest","period":"long","time":{"type":"BigNumber","hex":"0x649a2680"},"amount":{"type":"BigNumber","hex":"0x016a9bf37a"}}]}