{"lastDay":{"type":"BigNumber","hex":"0x4de6"},"rewards":[{"type":"interest","period":"long","time":{"type":"BigNumber","hex":"0x668dcf00"},"amount":{"type":"BigNumber","hex":"0x91dc2357"}},{"type":"interest","period":"long","time":{"type":"BigNumber","hex":"0x668f2080"},"amount":{"type":"BigNumber","hex":"0x91dc2357"}},{"type":"interest","period":"long","time":{"type":"BigNumber","hex":"0x66907200"},"amount":{"type":"BigNumber","hex":"0x91dc2357"}},{"type":"interest","period":"long","time":{"type":"BigNumber","hex":"0x6691c380"},"amount":{"type":"BigNumber","hex":"0xf34a9d4f"}},{"type":"interest","period":"long","time":{"type":"BigNumber","hex":"0x66931500"},"amount":{"type":"BigNumber","hex":"0xf34a9d4f"}},{"type":"interest","period":"long","time":{"type":"BigNumber","hex":"0x66946680"},"amount":{"type":"BigNumber","hex":"0xf34a9d4f"}},{"type":"interest","period":"long","time":{"type":"BigNumber","hex":"0x6695b800"},"amount":{"type":"BigNumber","hex":"0xf34a9d4f"}},{"type":"interest","period":"long","time":{"type":"BigNumber","hex":"0x66970980"},"amount":{"type":"BigNumber","hex":"0xf34a9d4f"}},{"type":"interest","period":"long","time":{"type":"BigNumber","hex":"0x66985b00"},"amount":{"type":"BigNumber","hex":"0xf34a9d4f"}},{"type":"interest","period":"long","time":{"type":"BigNumber","hex":"0x6699ac80"},"amount":{"type":"BigNumber","hex":"0xf46f14e2"}},{"type":"interest","period":"long","time":{"type":"BigNumber","hex":"0x669afe00"},"amount":{"type":"BigNumber","hex":"0xf46f14e2"}},{"type":"interest","period":"long","time":{"type":"BigNumber","hex":"0x669c4f80"},"amount":{"type":"BigNumber","hex":"0xf46f14e2"}},{"type":"interest","period":"long","time":{"type":"BigNumber","hex":"0x669da100"},"amount":{"type":"BigNumber","hex":"0xf46f14e2"}},{"type":"interest","period":"long","time":{"type":"BigNumber","hex":"0x669ef280"},"amount":{"type":"BigNumber","hex":"0xf46f14e2"}},{"type":"interest","period":"long","time":{"type":"BigNumber","hex":"0x66a04400"},"amount":{"type":"BigNumber","hex":"0xf46f14e2"}},{"type":"interest","period":"long","time":{"type":"BigNumber","hex":"0x66a19580"},"amount":{"type":"BigNumber","hex":"0xf46f14e2"}},{"type":"interest","period":"long","time":{"type":"BigNumber","hex":"0x66a2e700"},"amount":{"type":"BigNumber","hex":"0xf46f14e2"}},{"type":"interest","period":"long","time":{"type":"BigNumber","hex":"0x66a43880"},"amount":{"type":"BigNumber","hex":"0xf46f14e2"}},{"type":"interest","period":"long","time":{"type":"BigNumber","hex":"0x66a58a00"},"amount":{"type":"BigNumber","hex":"0xf46f14e2"}},{"type":"interest","period":"long","time":{"type":"BigNumber","hex":"0x66a6db80"},"amount":{"type":"BigNumber","hex":"0xf46f14e2"}},{"type":"interest","period":"long","time":{"type":"BigNumber","hex":"0x66a82d00"},"amount":{"type":"BigNumber","hex":"0xf46f14e2"}},{"type":"interest","period":"long","time":{"type":"BigNumber","hex":"0x66a97e80"},"amount":{"type":"BigNumber","hex":"0xf46f14e2"}},{"type":"interest","period":"long","time":{"type":"BigNumber","hex":"0x66aad000"},"amount":{"type":"BigNumber","hex":"0xf46f14e2"}},{"type":"interest","period":"long","time":{"type":"BigNumber","hex":"0x66ac2180"},"amount":{"type":"BigNumber","hex":"0xf67efe6e"}},{"type":"interest","period":"long","time":{"type":"BigNumber","hex":"0x66ad7300"},"amount":{"type":"BigNumber","hex":"0xf67efe6e"}},{"type":"interest","period":"long","time":{"type":"BigNumber","hex":"0x66aec480"},"amount":{"type":"BigNumber","hex":"0x0167449f6e"}},{"type":"interest","period":"long","time":{"type":"BigNumber","hex":"0x66b01600"},"amount":{"type":"BigNumber","hex":"0x0167449f6e"}},{"type":"interest","period":"long","time":{"type":"BigNumber","hex":"0x66b16780"},"amount":{"type":"BigNumber","hex":"0x0167ff52ce"}},{"type":"interest","period":"long","time":{"type":"BigNumber","hex":"0x66b2b900"},"amount":{"type":"BigNumber","hex":"0x0167ff52ce"}}]}